wordmill/__init__.py
wordmill/cache.py
wordmill/llm.py
wordmill/resources/__init__.py
wordmill/resources/api.py
wordmill/resources/routes.py
wordmill-0.0.2.dist-info/METADATA
wordmill-0.0.2.dist-info/WHEEL
wordmill-0.0.2.dist-info/licenses/LICENSE
wordmill-0.0.2.dist-info/RECORD
