Metadata-Version: 2.4
Name: wordmill
Version: 0.0.2
Summary: Document summarization API service
Project-URL: Homepage, https://github.com/RedHatInsights/wordmill
License-File: LICENSE
Requires-Python: >=3.12
Requires-Dist: flask
Requires-Dist: flask-caching
Requires-Dist: flask-cors
Requires-Dist: flask-restful
Requires-Dist: openai
Requires-Dist: python-dotenv
